odoo8_addon_medical_prescription_thread-8.0.1.0.0.99.dev2-py2.7-nspkg.pth
odoo8_addon_medical_prescription_thread-8.0.1.0.0.99.dev2.dist-info/top_level.txt
odoo8_addon_medical_prescription_thread-8.0.1.0.0.99.dev2.dist-info/WHEEL
odoo8_addon_medical_prescription_thread-8.0.1.0.0.99.dev2.dist-info/RECORD
odoo8_addon_medical_prescription_thread-8.0.1.0.0.99.dev2.dist-info/metadata.json
odoo8_addon_medical_prescription_thread-8.0.1.0.0.99.dev2.dist-info/DESCRIPTION.rst
odoo8_addon_medical_prescription_thread-8.0.1.0.0.99.dev2.dist-info/METADATA
odoo8_addon_medical_prescription_thread-8.0.1.0.0.99.dev2.dist-info/namespace_packages.txt
odoo_addons/medical_prescription_thread/__openerp__.py
odoo_addons/medical_prescription_thread/__init__.py
odoo_addons/medical_prescription_thread/README.rst
odoo_addons/medical_prescription_thread/models/medical_prescription_order.py
odoo_addons/medical_prescription_thread/models/medical_prescription_order_line.py
odoo_addons/medical_prescription_thread/models/__init__.py
odoo_addons/medical_prescription_thread/i18n/pt_BR.po
odoo_addons/medical_prescription_thread/views/medical_prescription_order_line_view.xml
odoo_addons/medical_prescription_thread/views/medical_prescription_order_view.xml
